{"v":1,"data":[{"id":"d2","matchUrl":"*mapgenie.io/tarkov/*","rules":[{"type":"normalOverride","match":"https://cdn.mapgenie.io/images/games/tarkov/markers.png?MTg4NzUx","replace":"https://raw.githubusercontent.com/odt1/Mapgenie.io-Tarkov-Better-Icons/main/res/markers.png","on":true},{"type":"normalOverride","match":"https://cdn.mapgenie.io/images/games/tarkov/markers@2x.png?MTg4NzUx","replace":"https://raw.githubusercontent.com/odt1/Mapgenie.io-Tarkov-Better-Icons/main/res/markers@2x.png","on":true}],"on":true}]}